README.rst
pybongtvapi.py
setup.cfg
setup.py
pybongtvapi.egg-info/PKG-INFO
pybongtvapi.egg-info/SOURCES.txt
pybongtvapi.egg-info/dependency_links.txt
pybongtvapi.egg-info/top_level.txt