Metadata-Version: 1.1
Name: pybongtvapi
Version: 0.2
Summary: a pythonic API for the bong.tv platform
Home-page: https://github.com/cmaugg/pybongtvapi
Author: Christian Maugg
Author-email: software@christianmaugg.de
License: UNKNOWN
Download-URL: https://github.com/cmaugg/pybongtvapi/tarball/0.2
Keywords: bong.tv pvr online video recorder epg electronic program guide
Platform: UNKNOWN
Classifier: Development Status :: 3 - Alpha
Classifier: Intended Audience :: Developers
Classifier: License :: OSI Approved :: MIT License
Classifier: Programming Language :: Python
Classifier: Programming Language :: Python :: 2
Classifier: Programming Language :: Python :: 2.6
Classifier: Programming Language :: Python :: 2.7
Classifier: Topic :: Software Development :: Libraries
